MANIFEST.in
README.md
pyproject.toml
setup.py
amuse_mosse.egg-info/PKG-INFO
amuse_mosse.egg-info/SOURCES.txt
amuse_mosse.egg-info/dependency_links.txt
amuse_mosse.egg-info/requires.txt
amuse_mosse.egg-info/top_level.txt
src/amuse/community/mosse/Makefile
src/amuse/community/mosse/__init__.py
src/amuse/community/mosse/_version.py
src/amuse/community/mosse/interface.f
src/amuse/community/mosse/interface.py
src/amuse/community/mosse/src/Makefile
src/amuse/community/mosse/src/README_MOBSE
src/amuse/community/mosse/src/comenv.f
src/amuse/community/mosse/src/const_mobse.h
src/amuse/community/mosse/src/deltat.f
src/amuse/community/mosse/src/dgcore.f
src/amuse/community/mosse/src/eddington.f
src/amuse/community/mosse/src/evolv1.f
src/amuse/community/mosse/src/evolv1_bis.f
src/amuse/community/mosse/src/evolv3.f
src/amuse/community/mosse/src/evolve.dat
src/amuse/community/mosse/src/fallback.f
src/amuse/community/mosse/src/hrdiag.f
src/amuse/community/mosse/src/kick.f
src/amuse/community/mosse/src/mlwind.f
src/amuse/community/mosse/src/mosse.f
src/amuse/community/mosse/src/mrenv.f
src/amuse/community/mosse/src/pisn.f
src/amuse/community/mosse/src/ran3.f
src/amuse/community/mosse/src/rl.f
src/amuse/community/mosse/src/sse.f
src/amuse/community/mosse/src/star.f
src/amuse/community/mosse/src/star.in
src/amuse/community/mosse/src/zcnsts.f
src/amuse/community/mosse/src/zdata.h
src/amuse/community/mosse/src/zfuncs.f
support/__init__.py
support/classifiers.py
support/config.py
support/generate_main.py
support/getsp.class
support/getsp.java
support/misc.py
support/setup_codes.py
support/version.py